static_base/__init__.py
static_base/static/base/css/bootstrap-grid.css
static_base/static/base/css/bootstrap-grid.css.map
static_base/static/base/css/bootstrap-grid.min.css
static_base/static/base/css/bootstrap-grid.min.css.map
static_base/static/base/css/bootstrap-reboot.css
static_base/static/base/css/bootstrap-reboot.css.map
static_base/static/base/css/bootstrap-reboot.min.css
static_base/static/base/css/bootstrap-reboot.min.css.map
static_base/static/base/css/bootstrap.css
static_base/static/base/css/bootstrap.css.map
static_base/static/base/css/bootstrap.min.css
static_base/static/base/css/bootstrap.min.css.map
static_base/static/base/css/bootstrap5.min.css
static_base/static/base/css/style-accordion.css
static_base/static/base/css/style-blog.css
static_base/static/base/css/style-box.css
static_base/static/base/css/style-btn.css
static_base/static/base/css/style-color.css
static_base/static/base/css/style-cubeportfolio.css
static_base/static/base/css/style-dropdown.css
static_base/static/base/css/style-font-icons.css
static_base/static/base/css/style-forms.css
static_base/static/base/css/style-general.css
static_base/static/base/css/style-google-iframe.css
static_base/static/base/css/style-gototop.css
static_base/static/base/css/style-icon-profile.css
static_base/static/base/css/style-icon-social.css
static_base/static/base/css/style-inverse-text.css
static_base/static/base/css/style-lightgallery.css
static_base/static/base/css/style-list-group.css
static_base/static/base/css/style-list.css
static_base/static/base/css/style-loading.css
static_base/static/base/css/style-menu-ham.css
static_base/static/base/css/style-menu-mega.css
static_base/static/base/css/style-navbar.css
static_base/static/base/css/style-overlay.css
static_base/static/base/css/style-pricing.css
static_base/static/base/css/style-reset.css
static_base/static/base/css/style-responsive.css
static_base/static/base/css/style-scroll-animations.css
django_static_base-0.4.2.dist-info/LICENSE
django_static_base-0.4.2.dist-info/METADATA
django_static_base-0.4.2.dist-info/WHEEL
django_static_base-0.4.2.dist-info/top_level.txt
django_static_base-0.4.2.dist-info/RECORD
